FRScraper/FRScraper.py
FRScraper/__init__.py
FRScraper-0.1.3.dist-info/LICENSE
FRScraper-0.1.3.dist-info/METADATA
FRScraper-0.1.3.dist-info/WHEEL
FRScraper-0.1.3.dist-info/top_level.txt
FRScraper-0.1.3.dist-info/RECORD
