Metadata-Version: 2.1
Name: FRScraper
Version: 0.1.3
Summary: Python module for Football Reference scraping and easy access to football data from various leagues
Home-page: https://github.com/GabrielPastorello/FRScraper
Author: Gabriel Speranza Pastorello
Author-email: gabriel.pastorello01@gmail.com
License: MIT
Keywords: football reference,scraper,premier league,la liga,ligue 1,serie a,bundesliga,eredivisie,football data
Classifier: Programming Language :: Python :: 3
Classifier: License :: OSI Approved :: MIT License
Classifier: Operating System :: OS Independent
Requires-Python: >=3.6
License-File: LICENSE
Requires-Dist: pandas >=2.2.2
Requires-Dist: numpy >=1.26.4
Requires-Dist: python-dateutil >=2.8.2
Requires-Dist: pytz >=2024.1
